conspire-0.4.0.dist-info/METADATA
conspire-0.4.0.dist-info/WHEEL
conspire-0.4.0.dist-info/licenses/LICENSE
conspire/__init__.py
conspire/conspire.cpython-312-x86_64-linux-gnu.so
conspire-0.4.0.dist-info/RECORD
