Metadata-Version: 2.4
Name: conspire
Version: 0.4.0
Classifier: License :: OSI Approved :: GNU General Public License v3 (GPLv3)
Classifier: Development Status :: 5 - Production/Stable
Classifier: Intended Audience :: Science/Research
Classifier: Topic :: Scientific/Engineering
Classifier: Programming Language :: Python
Classifier: Programming Language :: Rust
Requires-Dist: numpy
Requires-Dist: build ; extra == 'dist'
Requires-Dist: maturin ; extra == 'dist'
Requires-Dist: pytest ; extra == 'dist'
Requires-Dist: twine ; extra == 'dist'
Requires-Dist: matplotlib ; extra == 'docs'
Requires-Dist: maturin ; extra == 'docs'
Requires-Dist: pdoc ; extra == 'docs'
Requires-Dist: maturin ; extra == 'test'
Requires-Dist: pytest ; extra == 'test'
Requires-Dist: ruff ; extra == 'test'
Provides-Extra: dist
Provides-Extra: docs
Provides-Extra: test
License-File: LICENSE
Summary: The Python interface to conspire.
Author-email: "Michael R. Buche" <mrbuche@sandia.gov>
Requires-Python: >=3.10
Project-URL: Documentation, https://conspire.readthedocs.io
Project-URL: Homepage, https://mrbuche.github.io/conspire
Project-URL: Repository, https://github.com/mrbuche/conspire.py
